pipe_MIPS32.v
`timescale 1ns / 1ps
//////////////////////////////////////////////////////////////////////////////////
// Company: 
// Engineer: DARSHAN D SHANKAR
// 
// Create Date:    16:47:15 06/08/2019 
// Design Name: Behavioral Implementation of MIPS - 32 Processor with pipelining.
// Module Name:    pipe_MIPS32 
// Project Name: 
// Target Devices: 
// Tool versions: 
// Description: 
//
// Dependencies: 
//
// Revision: 
// Revision 0.01 - File Created
// Additional Comments: 
//
//////////////////////////////////////////////////////////////////////////////////
module pipe_MIPS32(clk1, clk2
    );
	input clk1, clk2;
	
	parameter WORD_SIZE = 32, TYPE_WORD_SIZE = 3;


	reg [WORD_SIZE-1:0] 		 PC, IF_ID_IR, IF_ID_NPC;
	reg [WORD_SIZE-1:0] 		 ID_EX_IR, ID_EX_NPC, ID_EX_A, ID_EX_B, ID_EX_Imm;
	reg [TYPE_WORD_SIZE-1:0] ID_EX_type, EX_MEM_type, MEM_WB_type;
	reg [WORD_SIZE-1:0]		 EX_MEM_IR, EX_MEM_ALUout, EX_MEM_B;
	reg 							 EX_MEM_cond;
	reg [WORD_SIZE-1:0]		 MEM_WB_IR, MEM_WB_ALUout, MEM_WB_LMD;

	reg [WORD_SIZE-1:0]		 REG [0:31];
	reg [WORD_SIZE-1:0]		 MEMORY [0:1023];
	
	parameter 	ADD = 6'b000000, SUB = 6'b000001, AND = 6'b000010, OR = 6'b000011,
					SLT = 6'b000100, MUL = 6'b000101, HLT = 6'b111111, LW = 6'b001000,
					SW  = 6'b001001, ADDI = 6'b001010, SUBI = 6'b001011, SLTI = 6'b001100,
					BNEQZ = 6'b001101, BEQZ =  6'b001110;
					
	parameter RR_ALU = 3'b000, RM_ALU = 3'b001, LOAD = 3'b010, STORE = 3'b011,
				 BRANCH = 3'b100, HALT = 3'b101;
	reg HALTED; 
	reg TAKEN_BRANCH;

	//IF - STAGE

	always @(posedge clk1)
		if (HALTED == 0)
		begin
			if(((EX_MEM_IR[31:26] == BEQZ) && (EX_MEM_cond == 1)) || 
			   ((EX_MEM_IR[31:26] == BNEQZ) && (EX_MEM_cond == 0)))
					begin
						IF_ID_IR     <= #2 MEMORY[EX_MEM_ALUout];
						TAKEN_BRANCH <= #2 1'b1;
						IF_ID_NPC    <= #2 EX_MEM_ALUout + 1;
						PC	          <= #2 EX_MEM_ALUout + 1;
					end
			else
				begin
					IF_ID_IR        <= #2 MEMORY[PC];
					IF_ID_NPC       <= #2 PC + 1;
					PC              <= #2 PC + 1;
					TAKEN_BRANCH  <= #2 0;
				end	
		end
	
	//ID - STAGE
	
	always @ (posedge clk2)
		if (HALTED == 0)
		begin
			if (IF_ID_IR[25:21] == 5'b00000) ID_EX_A <= 0;
			else ID_EX_A <= #2 REG[IF_ID_IR[25:21]]; //Rs
			
			if (IF_ID_IR[20:16] == 5'b00000) ID_EX_B <= 0;
			else ID_EX_B <= #2 REG[IF_ID_IR[20:16]]; //Rt
			
			ID_EX_NPC <= #2 IF_ID_NPC;
			ID_EX_IR  <= #2 IF_ID_IR;
			ID_EX_Imm <= #2 {{16{IF_ID_IR[15]}}, {IF_ID_IR[15:0]}};
			
			case (IF_ID_IR[31:26])
				ADD, SUB, AND, OR, SLT, MUL : ID_EX_type <= #2 RR_ALU;
				ADDI, SUBI, SLTI            : ID_EX_type <= #2 RM_ALU;
				LW                          : ID_EX_type <= #2 LOAD;
				SW                          : ID_EX_type <= #2 STORE;
				BNEQZ, BEQZ                 : ID_EX_type <= #2 BRANCH;
				HLT                         : ID_EX_type <= #2 HALT;
				default                     : ID_EX_type <= #2 HALT;
			endcase
		end	

	// EX - STAGE
	always @ (posedge clk1)
		if (HALTED == 0)
		begin
			EX_MEM_type   <= #2 ID_EX_type;
			EX_MEM_IR     <= #2 ID_EX_IR;
			//TAKEN_BRANCH  <= #2 0;
			
			case (ID_EX_type)
				RR_ALU : begin
								case (ID_EX_IR[31:26])
									ADD      : EX_MEM_ALUout <= #2 ID_EX_A + ID_EX_B;
									SUB      : EX_MEM_ALUout <= #2 ID_EX_A - ID_EX_B;
									AND      : EX_MEM_ALUout <= #2 ID_EX_A & ID_EX_B;
									OR       : EX_MEM_ALUout <= #2 ID_EX_A | ID_EX_B;
									SLT      : EX_MEM_ALUout <= #2 ID_EX_A < ID_EX_B;
									MUL      : EX_MEM_ALUout <= #2 ID_EX_A * ID_EX_B;
									default  : EX_MEM_ALUout <= #2 32'hxxxxxxxx;
								endcase
							end
				
				RM_ALU : begin
								case (ID_EX_IR[31:26])
									ADDI     : EX_MEM_ALUout <= #2 ID_EX_A + ID_EX_Imm;
									SUBI     : EX_MEM_ALUout <= #2 ID_EX_A - ID_EX_Imm;
									SLTI     : EX_MEM_ALUout <= #2 ID_EX_A < ID_EX_Imm;
									default  : EX_MEM_ALUout <= #2 32'hxxxxxxxx;
								endcase
							end

				LOAD, STORE : begin		
									 EX_MEM_ALUout <= #2 ID_EX_A + ID_EX_Imm;
									 EX_MEM_B      <= #2 ID_EX_B;
								  end

				BRANCH : begin
								EX_MEM_ALUout <= #2 ID_EX_NPC + ID_EX_Imm;
								EX_MEM_cond   <= #2 (ID_EX_A == 0);
							end
			endcase
		end

	// MEM - STAGE
	always @(posedge clk2)
		if (HALTED == 0)
		begin
			MEM_WB_type <= EX_MEM_type;
			MEM_WB_IR <= #2 EX_MEM_IR;
			
			case (EX_MEM_type)
				RR_ALU, RM_ALU : MEM_WB_ALUout <= #2 EX_MEM_ALUout;
				LOAD           : MEM_WB_LMD    <= #2 MEMORY[EX_MEM_ALUout];
				STORE          : if (TAKEN_BRANCH == 0) MEMORY[EX_MEM_ALUout] <= #2 EX_MEM_B;
			endcase
		end
		
	//WB - STAGE
	always @ (posedge clk1)
		begin
			if (TAKEN_BRANCH == 0)
			
			case (MEM_WB_type)
				RR_ALU : REG[MEM_WB_IR[15:11]] <= #2 MEM_WB_ALUout; // Rd
				RM_ALU : REG[MEM_WB_IR[20:16]] <= #2 MEM_WB_ALUout;
				LOAD   : REG[MEM_WB_IR[20:16]] <= #2 MEM_WB_LMD;
				HALT   : HALTED <= 1'b1;
			endcase
		end	

endmodule

test_pipe_MIPS32.v
`timescale 1ns / 1ps

////////////////////////////////////////////////////////////////////////////////
// Company: 
// Engineer: DARSHAN D SHANKAR
//
// Create Date:   19:28:09 06/08/2019
// Design Name:   pipe_MIPS32
// Module Name:  
// Project Name:  MIPS_32
// Target Device:  
// Tool versions:  
// Description: 
//
//
//
// Dependencies:
// 
// Revision:
// Revision 0.01 - File Created
// Additional Comments:
// 
////////////////////////////////////////////////////////////////////////////////

module test_pipe_MIPS32;

	// Inputs
	reg clk1;
	reg clk2;
	integer k;

	parameter 	ADD = 6'b000000, SUB = 6'b000001, AND = 6'b000010, OR = 6'b000011,
					SLT = 6'b000100, MUL = 6'b000101, HLT = 6'b111111, LW = 6'b001000,
					SW  = 6'b001001, ADDI = 6'b001010, SUBI = 6'b001011, SLTI = 6'b001100,
					BNEQZ = 6'b001101, BEQZ =  6'b001110;

	parameter R0 = 5'd0, R1 = 5'd1, R2 = 5'd2, R3=5'd3, R4=5'd4, R5 = 5'd5, R6 = 5'd6, R7 = 5'd7, R8 = 5'd8, R9 = 5'd9,
			R10 = 5'd10, R11 = 5'd11, R12 = 5'd12, R13 = 5'd13, R14 = 5'd14, R15 = 5'd15, R16 = 5'd16, R17 = 5'd17, R18 = 5'd18,
			 R19 = 5'd19, R20 = 5'd20, R21 = 5'd21, R22 = 5'd22, R23 = 5'd23, R24 = 5'd24, R25 = 5'd25, R26 = 5'd26, R27 = 5'd27,
			R28 = 5'd28, R29 = 5'd29, R30 = 5'd30, R31 = 5'd31;		

	// Instantiate the Unit Under Test (UUT)
	pipe_MIPS32 uut (
		.clk1(clk1), 
		.clk2(clk2)
	);

	initial begin
		// Initialize Inputs
		uut.PC = 0;
		clk1 = 0;
		clk2 = 0;
		$monitor("PC = %d, IR = %h, ALUout = %d", uut.PC, uut.IF_ID_IR, uut.EX_MEM_ALUout);
		repeat(20)
			begin
				#5 clk1 = 1; #5 clk1 = 0;
				#5 clk2 = 1; #5 clk2 = 0;
			end
	end
	
	initial
		begin
			// for (k=0; k<31; k=k+1) uut.REG[k] = k; 
			uut.MEMORY[0] <= {ADDI,R0,R1,16'd10};
			uut.MEMORY[1] <= {ADDI,R0,R2,16'd20};
			uut.MEMORY[2] <= {ADDI,R0,R3,16'd25};
			uut.MEMORY[3] <= 32'h0ce77800;
			uut.MEMORY[4] <= 32'h0ce77800;
			uut.MEMORY[5] <= {ADD,R1,R2,R4,11'd0};
			uut.MEMORY[6] <= 32'h0ce77800;
			uut.MEMORY[7] <= {ADD,R4,R3,R5,11'd0};
			uut.MEMORY[8] <= {HLT,26'd0};

			// uut.MEMORY[0] <= {ADD,R2,R1,R28,11'd0};
			// uut.MEMORY[1] <= {HLT,26'd0};
			

			uut.HALTED = 0;
			uut.PC = 0;
			uut.TAKEN_BRANCH = 0;
			
			#280 for (k=0; k<6; k=k+1) $display ("R%1d - %2d ", k, uut.REG[k]);
		end
      
	initial
		begin
			$dumpfile ("mips.vcd");
			$dumpvars (0, test_pipe_MIPS32);
			#300 $finish;
		end	
endmodule

mips.vcd
$date
	Sat Jun 08 22:53:10 2019
$end
$version
	Icarus Verilog
$end
$timescale
	1ps
$end
$scope module test_pipe_MIPS32 $end
$var reg 1 ! clk1 $end
$var reg 1 " clk2 $end
$var integer 32 # k [31:0] $end
$scope module uut $end
$var wire 1 ! clk1 $end
$var wire 1 " clk2 $end
$var reg 32 $ EX_MEM_ALUout [31:0] $end
$var reg 32 % EX_MEM_B [31:0] $end
$var reg 32 & EX_MEM_IR [31:0] $end
$var reg 1 ' EX_MEM_cond $end
$var reg 3 ( EX_MEM_type [2:0] $end
$var reg 1 ) HALTED $end
$var reg 32 * ID_EX_A [31:0] $end
$var reg 32 + ID_EX_B [31:0] $end
$var reg 32 , ID_EX_IR [31:0] $end
$var reg 32 - ID_EX_Imm [31:0] $end
$var reg 32 . ID_EX_NPC [31:0] $end
$var reg 3 / ID_EX_type [2:0] $end
$var reg 32 0 IF_ID_IR [31:0] $end
$var reg 32 1 IF_ID_NPC [31:0] $end
$var reg 32 2 MEM_WB_ALUout [31:0] $end
$var reg 32 3 MEM_WB_IR [31:0] $end
$var reg 32 4 MEM_WB_LMD [31:0] $end
$var reg 3 5 MEM_WB_type [2:0] $end
$var reg 32 6 PC [31:0] $end
$var reg 1 7 TAKEN_BRANCH $end
$upscope $end
$upscope $end
$enddefinitions $end
#0
$dumpvars
07
b0 6
bx 5
bx 4
bx 3
bx 2
bx 1
bx 0
bx /
bx .
bx -
bx ,
bx +
bx *
0)
bx (
x'
bx &
bx %
bx $
bx #
0"
0!
$end
#5000
1!
#7000
b1 6
b1 1
b101000000000010000000000001010 0
#10000
0!
#15000
b0 *
1"
#17000
b1 /
b1010 -
b101000000000010000000000001010 ,
b1 .
#20000
0"
#25000
1!
#27000
b1010 $
b101000000000010000000000001010 &
b1 (
b10 6
b10 1
b101000000000100000000000010100 0
#30000
0!
#35000
b1 5
1"
#37000
b1010 2
b101000000000010000000000001010 3
b10100 -
b101000000000100000000000010100 ,
b10 .
#40000
0"
#45000
1!
#47000
b11 6
b11 1
b101000000000110000000000011001 0
b10100 $
b101000000000100000000000010100 &
#50000
0!
#55000
1"
#57000
b11001 -
b101000000000110000000000011001 ,
b11 .
b10100 2
b101000000000100000000000010100 3
#60000
0"
#65000
1!
#67000
b11001 $
b101000000000110000000000011001 &
b100 6
b100 1
b1100111001110111100000000000 0
#70000
0!
#75000
1"
#77000
b11001 2
b101000000000110000000000011001 3
b0 /
b111100000000000 -
b1100111001110111100000000000 ,
b100 .
bx *
#80000
0"
#85000
1!
#87000
b101 6
b101 1
bx $
b1100111001110111100000000000 &
b0 (
#90000
0!
#95000
b0 5
1"
#97000
b101 .
bx 2
b1100111001110111100000000000 3
#100000
0"
#105000
1!
#107000
b110 6
b110 1
b1000100010000000000000 0
#110000
0!
#115000
1"
#117000
b10000000000000 -
b1000100010000000000000 ,
b110 .
b10100 +
b1010 *
#120000
0"
#125000
1!
#127000
b111 6
b111 1
b1100111001110111100000000000 0
b11110 $
b1000100010000000000000 &
#130000
0!
#135000
1"
#137000
b111100000000000 -
b1100111001110111100000000000 ,
b111 .
bx +
bx *
b11110 2
b1000100010000000000000 3
#140000
0"
#145000
1!
#147000
bx $
b1100111001110111100000000000 &
b1000 6
b1000 1
b100000110010100000000000 0
#150000
0!
#155000
1"
#157000
bx 2
b1100111001110111100000000000 3
b10100000000000 -
b100000110010100000000000 ,
b1000 .
b11001 +
b11110 *
#160000
0"
#165000
1!
#167000
b1001 6
b1001 1
b11111100000000000000000000000000 0
b110111 $
b100000110010100000000000 &
#170000
0!
#175000
b0 +
b0 *
1"
#177000
b101 /
b0 -
b11111100000000000000000000000000 ,
b1001 .
b110111 2
b100000110010100000000000 3
#180000
0"
#185000
1!
#187000
b11111100000000000000000000000000 &
b101 (
b1010 6
b1010 1
bx 0
#190000
0!
#195000
b101 5
1"
#197000
b11111100000000000000000000000000 3
bx -
bx ,
b1010 .
bx +
bx *
#200000
0"
#205000
1)
1!
#207000
b1011 6
b1011 1
bx &
#210000
0!
#215000
1"
#220000
0"
#225000
1!
#230000
0!
#235000
1"
#240000
0"
#245000
1!
#250000
0!
#255000
1"
#260000
0"
#265000
1!
#270000
0!
#275000
1"
#280000
0"
b110 #
